LICENSE
README.md
setup.py
dectree/__init__.py
dectree/dectree.py
dectree.egg-info/PKG-INFO
dectree.egg-info/SOURCES.txt
dectree.egg-info/dependency_links.txt
dectree.egg-info/requires.txt
dectree.egg-info/top_level.txt