Metadata-Version: 2.1
Name: dectree
Version: 0.1.0
Summary: A tool to explore decision trees
Home-page: https://github.com/Dessia-tech/dectree
Author: DessIA
Author-email: root@dessia.tech
License: UNKNOWN
Platform: UNKNOWN
License-File: LICENSE
